lclayout/__init__.py
lclayout/data_types.py
lclayout/extrema.py
lclayout/routing_graph.py
lclayout/standalone.py
lclayout/tech_util.py
lclayout/drc_cleaner/__init__.py
lclayout/drc_cleaner/base.py
lclayout/drc_cleaner/drc_cleaner.py
lclayout/drc_cleaner/drc_theorem_proofs.py
lclayout/drc_cleaner/standalone.py
lclayout/graphrouter/__init__.py
lclayout/graphrouter/graphrouter.py
lclayout/graphrouter/hv_router.py
lclayout/graphrouter/lp_router.py
lclayout/graphrouter/min_area_router.py
lclayout/graphrouter/multi_via_router.py
lclayout/graphrouter/pathfinder.py
lclayout/graphrouter/pathfinder_experimental.py
lclayout/graphrouter/pyo3_graphrouter.py
lclayout/graphrouter/signal_router.py
lclayout/graphrouter/smt_router.py
lclayout/layout/__init__.py
lclayout/layout/cell_template.py
lclayout/layout/geometry_helpers.py
lclayout/layout/grid.py
lclayout/layout/grid_helpers.py
lclayout/layout/layers.py
lclayout/layout/notch_removal.py
lclayout/layout/transistor.py
lclayout/lef/__init__.py
lclayout/lef/types.py
lclayout/place/__init__.py
lclayout/place/euler_placer.py
lclayout/place/eulertours.py
lclayout/place/partition.py
lclayout/place/place.py
lclayout/place/pyo3_place.py
lclayout/place/smt_placer.py
librecell_layout-0.0.5.dist-info/LICENSE
librecell_layout-0.0.5.dist-info/METADATA
librecell_layout-0.0.5.dist-info/WHEEL
librecell_layout-0.0.5.dist-info/entry_points.txt
librecell_layout-0.0.5.dist-info/top_level.txt
librecell_layout-0.0.5.dist-info/RECORD
