Metadata-Version: 2.1
Name: librecell-layout
Version: 0.0.5
Summary: CMOS standard cell generator.
Home-page: https://codeberg.org/tok/librecell
Author: T. Kramer
Author-email: dont@spam.me
License: OHL-S v2.0
Keywords: cmos cell generator layout klayout vlsi asic
Platform: UNKNOWN
Classifier: Development Status :: 3 - Alpha
Classifier: Topic :: Scientific/Engineering
Classifier: Topic :: Scientific/Engineering :: Electronic Design Automation (EDA)
Classifier: Programming Language :: Python :: 3
Requires-Dist: librecell-common
Requires-Dist: klayout
Requires-Dist: numpy
Requires-Dist: networkx
Requires-Dist: pyspice
Requires-Dist: scipy
Requires-Dist: liberty-parser
Requires-Dist: pysmt
Requires-Dist: z3-solver
Requires-Dist: pulp
